softpro_elk_grpc_logger/__init__.py
softpro_elk_grpc_logger/logger.py
softpro_elk_grpc_logger-0.1.0.dist-info/LICENSE
softpro_elk_grpc_logger-0.1.0.dist-info/METADATA
softpro_elk_grpc_logger-0.1.0.dist-info/WHEEL
softpro_elk_grpc_logger-0.1.0.dist-info/top_level.txt
softpro_elk_grpc_logger-0.1.0.dist-info/RECORD
