Metadata-Version: 2.1
Name: softpro_elk_grpc_logger
Version: 0.1.0
Summary: A small package for ELK structure logging for python microservices
Home-page: https://git.softpro.ua/service/python_logger
Author: Verenych Danylo
Author-email: karate3@gmail.com
Classifier: Programming Language :: Python :: 3
Classifier: License :: OSI Approved :: MIT License
Classifier: Operating System :: OS Independent
Classifier: Development Status :: 4 - Beta
Classifier: Intended Audience :: Developers
Classifier: Topic :: Software Development :: Libraries :: Python Modules
Classifier: Topic :: System :: Logging
Requires-Python: >=3.6
License-File: LICENSE
